{"Lamp": {"head": {"position_lamp_head": {"description": "Position the lamp head according to the lighting needs.", "actions": ["rotate['head']"]}, "clean_head_surface": {"description": "Clean the surface of the lamp head to ensure maximum lighting efficiency.", "actions": ["wipe['head']"]}, "readjust_lamp_head": {"description": "Readjust the position of the lamp head to its original position.", "actions": ["rotate['head']", "rotate['head']", "rotate['head']"]}, "adjust_lamp_head": {"description": "Adjust the head of the lamp to change the light direction", "actions": ["rotate['head']"]}, "clean_lamp_head": {"description": "Clean the head of the Lamp to remove dust or any particles", "actions": ["wipe['head']"]}, "rotateLampHead": {"description": "Rotate the head of the lamp to adjust the light direction.", "actions": ["rotate['head']"]}, "rotate_lamp_head": {"description": "Rotate the lamp head to adjust the light direction.", "actions": ["rotate['head']"]}}, "lamp_base": {"cleanup_lamp_base": {"description": "Clean up the lamp base to maintain the lamp's aesthetic appeal.", "actions": ["wipe['lamp_base']"]}, "clean_lamp_base": {"description": "Clean the base of the lamp to remove dust or any particles", "actions": ["wipe['lamp_base']"]}, "general": {"cleanLampBase": {"description": "Clean the base of the lamp to remove dust or any other particles.", "actions": ["wipe['lamp_base']"]}}}, "general": {"total_lamp_cleanup": {"description": "Perform a total clean up of the lamp which involves cleaning the lamp base and head.", "actions": ["wipe['lamp_base']", "wipe['head']"]}, "lamp_position_adjustment": {"description": "Perform an overall lamp position adjustment. This involves adjusting the lamp head thrice to get it to the right position.", "actions": ["rotate['head']", "rotate['head']", "rotate['head']"]}, "full_lamp_maintenance": {"description": "Perform full maintenance of the lamp. This involves cleaning the entire lamp and readjusting the lamp head.", "actions": ["wipe['lamp_base']", "wipe['head']", "rotate['head']", "rotate['head']", "rotate['head']"]}, "overall_lamp_maintenance": {"description": "Perform overall maintenance, adjust the head and clean the lamp", "actions": ["rotate['head']", "wipe['head']", "wipe['lamp_base']"]}, "clean_whole_lamp": {"description": "Clean the whole Lamp, including the head and base", "actions": ["wipe['head']", "wipe['lamp_base']"]}, "cleanWholeLamp": {"description": "Clean the entire lamp including the head and base.", "actions": ["wipe['head']", "wipe['lamp_base']"]}, "rotate_and_clean_head": {"description": "Rotate the lamp head and clean it.", "actions": ["rotate['head']", "wipe['head']"]}}}}