{"Toilet": {"lever": {"rotate_lever_double_flush": {"description": "Rotate the lever twice for a double flush.", "actions": ["rotate['lever']", "rotate['lever']"]}, "clean_lever_meticulously": {"description": "Clean the lever thoroughly to ensure sanitation.", "actions": ["wipe['lever']"]}, "rotate_lever_again": {"description": "Rotate the lever again for double flushing.", "actions": ["rotate['lever']"]}, "rotate_lever": {"description": "Rotate the toilet lever to flush the toilet.", "actions": ["rotate['lever']"]}, "press_lever": {"description": "Press the toilet lever to flush the toilet.", "actions": ["press['lever']"]}, "clean_lever": {"description": "Clean the lever to maintain cleanliness and hygiene.", "actions": ["wipe['lever']"]}}, "pump_lid": {"wipe_pump_lid_thoroughly": {"description": "Wipe the pump lid thoroughly to ensure it is clean.", "actions": ["wipe['pump_lid']"]}, "press_pump_lid_to_secure": {"description": "Press the pump lid to make sure it is secure.", "actions": ["press['pump_lid']"]}, "wipe_pump_lid": {"description": "Wipe the pump lid to keep it clean.", "actions": ["wipe['pump_lid']"]}, "press_pump_lid": {"description": "Press the pump lid to ensure it is properly in place.", "actions": ["press['pump_lid']"]}, "clean_pump_lid": {"description": "Clean the pump lid to maintain cleanliness and hygiene.", "actions": ["wipe['pump_lid']"]}}, "opened_lid": {"close_lid_after_usage": {"description": "Close the toilet lid after usage by swinging it down to the closed position.", "actions": ["flap_close['lid']"]}, "wipe_open_lid_again": {"description": "Wipe the opened lid once more to make sure it's clean.", "actions": ["wipe['lid']"]}, "keep_lid_open": {"description": "Keep the lid in the open position.", "actions": ["StatusComplete"]}, "close_lid": {"description": "Close the toilet lid by swinging it down to the closed position.", "actions": ["flap_close['lid']"]}, "clean_open_lid": {"description": "Clean the inside of the lid while it is open.", "actions": ["wipe['lid']"]}}, "closed_lid": {"open_lid_before_usage": {"description": "Lift the toilet lid before usage to the open position.", "actions": ["flap_open['lid']"]}, "wipe_closed_lid_again": {"description": "Wipe the closed lid again for extra cleanliness.", "actions": ["wipe['lid']"]}, "keep_lid_closed": {"description": "Keep the toilet lid in the closed position.", "actions": ["StatusComplete"]}, "open_lid": {"description": "Lift the toilet lid to the open position.", "actions": ["flap_open['lid']"]}, "clean_closed_lid": {"description": "Clean the outer surface of the lid while it is closed.", "actions": ["wipe['lid']"]}}, "opened_seat": {"close_seat_after_usage": {"description": "Lower the toilet seat after usage to the closed position", "actions": ["flap_close['seat']"]}, "wipe_open_seat_again": {"description": "Wipe the opened seat again to ensure hygiene and cleanliness.", "actions": ["wipe['seat']"]}, "keep_seat_open": {"description": "Maintain the toilet seat in the open status.", "actions": ["StatusComplete"]}, "close_seat": {"description": "Lower the toilet seat to the closed position", "actions": ["flap_close['seat']"]}, "clean_opened_seat": {"description": "Clean the toilet seat while it's opened.", "actions": ["wipe['seat']"]}, "clean_open_seat": {"description": "Clean the toilet seat when it is open.", "actions": ["wipe['seat']"]}}, "closed_seat": {"open_seat_before_usage": {"description": "Raise the toilet seat before usage to the open position.", "actions": ["flap_open['seat']"]}, "wipe_closed_seat_again": {"description": "Wipe the closed seat again for maintaining cleanliness.", "actions": ["wipe['seat']"]}, "keep_seat_closed": {"description": "Keep the toilet seat in the closed position.", "actions": ["StatusComplete"]}, "open_seat": {"description": "Raise the toilet seat to the open position.", "actions": ["flap_open['seat']"]}, "clean_closed_seat": {"description": "Clean the toilet seat while it's closed.", "actions": ["wipe['seat']"]}}, "toilet_body": {"clean_toilet_body_thoroughly": {"description": "Clean the entire toilet body thoroughly to ensure sanitation.", "actions": ["wipe['toilet_body']"]}, "wipe_toilet_body_again": {"description": "Wipe the entire toilet body once more for thorough cleaning.", "actions": ["wipe['toilet_body']"]}, "keep_toilet_body_clean": {"description": "Maintain the cleanliness of the entire outer surface of the toilet body.", "actions": ["StatusComplete"]}, "clean_toilet_body": {"description": "Clean the entire outer surface of the toilet body.", "actions": ["wipe['toilet_body']"]}}, "general": {"clean_all_parts_thoroughly": {"description": "Clean all parts of the toilet thoroughly for perfect sanitation.", "actions": ["wipe['toilet_body']", "wipe['seat']", "wipe['lid']", "wipe['pump_lid']", "wipe['lever']"]}, "clean_all_parts_again": {"description": "Clean all the parts again to make sure no dirt is left.", "actions": ["wipe['toilet_body']", "wipe['seat']", "wipe['lid']", "wipe['pump_lid']", "wipe['lever']"]}, "check_all_components": {"description": "Check the overall condition of the toilet including the seat, lid, lever, pump lid, and toilet body.", "actions": ["StatusComplete"]}, "clean_whole_toilet": {"description": "Clean the entire toilet including the seat, lid, lever, pump lid, and toilet body.", "actions": ["wipe['lever']", "wipe['pump_lid']", "wipe['lid']", "wipe['seat']", "wipe['toilet_body']"]}, "rotate_lever": {"description": "Rotate the toilet lever to flush the toilet.", "actions": ["rotate['lever']"]}, "press_lever": {"description": "Press the lever down to flush the toilet.", "actions": ["press['lever']"]}, "full_toilet_clean": {"description": "Clean entire toilet.", "actions": ["wipe['lever']", "wipe['pump_lid']", "wipe['lid']", "wipe['seat']", "wipe['toilet_body']"]}}}}